stock_prophet/__init__.py
stock_prophet/app/__init__.py
stock_prophet/app/app.py
stock_prophet/model/__init__.py
stock_prophet/model/btc_model.py
stock_prophet-0.2.0.dist-info/METADATA
stock_prophet-0.2.0.dist-info/WHEEL
stock_prophet-0.2.0.dist-info/top_level.txt
stock_prophet-0.2.0.dist-info/RECORD
