Metadata-Version: 2.1
Name: stock-prophet
Version: 0.2.0
Summary: UNKNOWN
Home-page: UNKNOWN
License: UNKNOWN
Platform: UNKNOWN
Requires-Dist: flask (==2.0.1)
Requires-Dist: prophet (==1.0.1)
Requires-Dist: yfinance (==0.1.59)
